Blauwal3_DataFusion-0.1.11-py3.10-nspkg.pth
orangecontrib/datafusion/__init__.py
orangecontrib/datafusion/i18n_config.py
orangecontrib/datafusion/models.py
orangecontrib/datafusion/movielens.py
orangecontrib/datafusion/datasets/actors.csv
orangecontrib/datafusion/datasets/movies.csv
orangecontrib/datafusion/datasets/ratings.csv
orangecontrib/datafusion/locale/datafusion.de.yml
orangecontrib/datafusion/locale/datafusion.en.yml
orangecontrib/datafusion/locale/datafusion.zh.yml
orangecontrib/datafusion/tutorials/510-collective-tri-factorization.ows
orangecontrib/datafusion/tutorials/510-latent-factors.ows
orangecontrib/datafusion/tutorials/510-tri-factorization.ows
orangecontrib/datafusion/tutorials/__init__.py
orangecontrib/datafusion/widgets/__init__.py
orangecontrib/datafusion/widgets/graphview.py
orangecontrib/datafusion/widgets/owchaining.py
orangecontrib/datafusion/widgets/owcompletionscoring.py
orangecontrib/datafusion/widgets/owfusiongraph.py
orangecontrib/datafusion/widgets/owimdbactors.py
orangecontrib/datafusion/widgets/owlatentfactors.py
orangecontrib/datafusion/widgets/owmeanfuser.py
orangecontrib/datafusion/widgets/owmoviegenres.py
orangecontrib/datafusion/widgets/owmovieratings.py
orangecontrib/datafusion/widgets/owsamplematrix.py
orangecontrib/datafusion/widgets/owtabletorelation.py
orangecontrib/datafusion/widgets/icons/Category-Fusion.svg
orangecontrib/datafusion/widgets/icons/CompletionScoring.svg
orangecontrib/datafusion/widgets/icons/FusionGraph.svg
orangecontrib/datafusion/widgets/icons/IMDbActors.svg
orangecontrib/datafusion/widgets/icons/LatentChaining.svg
orangecontrib/datafusion/widgets/icons/LatentFactors.svg
orangecontrib/datafusion/widgets/icons/MatrixSampler.svg
orangecontrib/datafusion/widgets/icons/MeanFuser.svg
orangecontrib/datafusion/widgets/icons/MovieGenres.svg
orangecontrib/datafusion/widgets/icons/MovieRatings.svg
orangecontrib/datafusion/widgets/icons/TableToRelation.svg
Blauwal3_DataFusion-0.1.11.dist-info/LICENSE
Blauwal3_DataFusion-0.1.11.dist-info/METADATA
Blauwal3_DataFusion-0.1.11.dist-info/WHEEL
Blauwal3_DataFusion-0.1.11.dist-info/entry_points.txt
Blauwal3_DataFusion-0.1.11.dist-info/namespace_packages.txt
Blauwal3_DataFusion-0.1.11.dist-info/top_level.txt
Blauwal3_DataFusion-0.1.11.dist-info/RECORD
